inmanta_plugins/ssh/__init__.py
inmanta_plugins/ssh/setup.cfg
inmanta_plugins/ssh/model/_init.cf
inmanta_plugins/ssh/templates/authorized_keys
inmanta_module_ssh-1.0.5.dist-info/METADATA
inmanta_module_ssh-1.0.5.dist-info/WHEEL
inmanta_module_ssh-1.0.5.dist-info/top_level.txt
inmanta_module_ssh-1.0.5.dist-info/RECORD
