Metadata-Version: 2.1
Name: inmanta-module-ssh
Version: 1.0.5
License: Apache 2.0
Requires-Dist: inmanta-module-fs
Requires-Dist: inmanta-module-std
Requires-Dist: inmanta-module-mitogen
